README.rst
setup.py
abp/__init__.py
abp/anders_cz.py
abp/build_tables.py
abp/clifford.py
abp/graphstate.py
abp/nxgraphstate.py
abp/qi.py
abp/stabilizer.py
abp/tables.py
abp/util.py
abp.egg-info/PKG-INFO
abp.egg-info/SOURCES.txt
abp.egg-info/dependency_links.txt
abp.egg-info/requires.txt
abp.egg-info/top_level.txt