Metadata-Version: 1.0
Name: abp
Version: 0.6.3
Summary: Port of C++ due to Simon Anders and Hans J Briegel
Home-page: https://github.com/peteshadbolt/abp
Author: Pete Shadbolt
Author-email: hello@peteshadbolt.co.uk
License: UNKNOWN
Keywords: quantum
Platform: UNKNOWN
